subtrace/__init__.py
subtrace/subtrace-linux-amd64
subtrace/subtrace-linux-arm64
subtrace-0.390.dist-info/METADATA
subtrace-0.390.dist-info/WHEEL
subtrace-0.390.dist-info/top_level.txt
subtrace-0.390.dist-info/RECORD
