Metadata-Version: 2.4
Name: subtrace
Version: 0.390
Summary: Subtrace helper for Python apps
Home-page: https://subtrace.dev
Author: Subtrace, Inc.
Author-email: support@subtrace.dev
License: BSD
Project-URL: Docs, https://subtrace.dev/docs
Project-URL: Github, https://github.com/subtrace/subtrace
Keywords: subtrace tracing api observability devtools
Classifier: Programming Language :: Python
Classifier: Programming Language :: Python :: 2
Classifier: Programming Language :: Python :: 3
Requires-Python: >=3.9
Requires-Dist: truststore
Dynamic: author
Dynamic: author-email
Dynamic: classifier
Dynamic: home-page
Dynamic: keywords
Dynamic: license
Dynamic: project-url
Dynamic: requires-dist
Dynamic: requires-python
Dynamic: summary
